{
  "sections": {
    "165970559810c3db58": {
      "type": "image-with-text-overlay",
      "disabled": true,
      "settings": {
        "image": "shopify:\/\/shop_images\/landing-1.jpg",
        "title": "Online Persian Grocery Made Easy",
        "content": "<p><a href=\"\/collections\" title=\"All collections\">start shoping<\/a><\/p><p><\/p>",
        "show_image_overlay": true,
        "color": "#ffffff"
      }
    },
    "slideshow": {
      "type": "slideshow",
      "blocks": {
        "74d92554-7dd4-4a28-91ea-ff25537a114d": {
          "type": "image",
          "settings": {
            "image": "shopify:\/\/shop_images\/baner11-1401-08-30_copy.jpg",
            "mobile_image": "shopify:\/\/shop_images\/baner2-750-1100_copy2.jpg",
            "show_overlay": false,
            "overlay_opacity": 30,
            "text_color": "#ffffff",
            "title": "",
            "content": "",
            "content_position": "middle_center",
            "button_background": "#ff0000",
            "button_text_color": "#ffffff",
            "button_text": "Start Shopping",
            "link": "shopify:\/\/collections"
          }
        },
        "6298f733-2db1-450f-9d19-b38fe1140504": {
          "type": "image",
          "settings": {
            "image": "shopify:\/\/shop_images\/baner22-1401-08-30.jpg",
            "mobile_image": "shopify:\/\/shop_images\/baner11-750-1100_f380cbb9-fe9c-4368-b711-cb8ec9a6d372.jpg",
            "show_overlay": false,
            "overlay_opacity": 35,
            "text_color": "#121251",
            "title": "",
            "content": "",
            "content_position": "bottom_center",
            "button_background": "#ee0000",
            "button_text_color": "#ffffff",
            "button_text": "Start Shopping",
            "link": "shopify:\/\/pages\/all-collections"
          }
        },
        "dec882c9-04da-475a-a36c-0269dba5f5db": {
          "type": "image",
          "disabled": true,
          "settings": {
            "image": "shopify:\/\/shop_images\/baner2-d.jpg",
            "mobile_image": "shopify:\/\/shop_images\/baner11-750-1100.jpg",
            "show_overlay": false,
            "overlay_opacity": 30,
            "text_color": "#ffffff",
            "title": "",
            "content": "",
            "content_position": "middle_center",
            "button_background": "#ed1c24",
            "button_text_color": "#ffffff",
            "button_text": "Order Now",
            "link": "shopify:\/\/collections"
          }
        }
      },
      "block_order": [
        "74d92554-7dd4-4a28-91ea-ff25537a114d",
        "6298f733-2db1-450f-9d19-b38fe1140504",
        "dec882c9-04da-475a-a36c-0269dba5f5db"
      ],
      "settings": {
        "edge_to_edge": true,
        "section_size": "large",
        "carousel_effect": "slide",
        "autoplay": true,
        "cycle_speed": 4
      }
    },
    "1636241720a09de843": {
      "type": "offers",
      "disabled": true,
      "blocks": {
        "1636241720a09de843-0": {
          "type": "offer",
          "settings": {
            "image": "shopify:\/\/shop_images\/iconmonstr-magnifier-6-240_1.png",
            "title": "Browse",
            "content": "<p>Browse our selection of quality<br\/>products.<\/p>"
          }
        },
        "1636241720a09de843-1": {
          "type": "offer",
          "settings": {
            "image": "shopify:\/\/shop_images\/iconmonstr-check-mark-14-240.png",
            "title": "Order",
            "content": "<p>Easily place your<br\/>order on our website.<\/p>"
          }
        },
        "5a65015f-b598-45b2-9c8b-ba4fda562d25": {
          "type": "offer",
          "settings": {
            "image": "shopify:\/\/shop_images\/iconmonstr-delivery-6-240_2.png",
            "title": "Receive",
            "content": "<p>We'll deliver your order in under 3 hours.<\/p>"
          }
        }
      },
      "block_order": [
        "1636241720a09de843-0",
        "1636241720a09de843-1",
        "5a65015f-b598-45b2-9c8b-ba4fda562d25"
      ],
      "settings": {
        "items_per_row": 3,
        "stack_mobile": true
      }
    },
    "1637542558ac9160e1": {
      "type": "text-with-icons",
      "blocks": {
        "16375425587d2f86b0-0": {
          "type": "item",
          "settings": {
            "icon": "bi-alert",
            "title": "",
            "content": "<h3><strong>Nowruz Sweets                                             <\/strong><\/h3><h4><strong>ON SALE<\/strong><\/h4><p>Until 13-Bedar (April 2nd)<\/p>"
          }
        },
        "16375425587d2f86b0-1": {
          "type": "item",
          "disabled": true,
          "settings": {
            "icon": "bi-fast-delivery",
            "title": "Fast Delivery",
            "content": "<p>Current average delivery time  is  2:51 hours.<\/p>"
          }
        },
        "16375425587d2f86b0-2": {
          "type": "item",
          "disabled": true,
          "settings": {
            "icon": "bi-customer-support",
            "title": "Free Delivery",
            "content": "<p>Orders above $30 in Selected Vancouver area<\/p>"
          }
        },
        "16375425587d2f86b0-3": {
          "type": "item",
          "disabled": true,
          "settings": {
            "icon": "bi-secure-payment",
            "title": "Secure payments",
            "content": "<p>Short content about your store<\/p>"
          }
        }
      },
      "block_order": [
        "16375425587d2f86b0-0",
        "16375425587d2f86b0-1",
        "16375425587d2f86b0-2",
        "16375425587d2f86b0-3"
      ],
      "settings": {
        "stack_mobile": false
      }
    },
    "collection-list": {
      "type": "collection-list",
      "blocks": {
        "collection-1": {
          "type": "collection",
          "disabled": true,
          "settings": {
            "collection": "persian-cooking-essentials",
            "link": ""
          }
        },
        "c07d7cd8-49e6-48e6-b89a-8cd1af82b4a1": {
          "type": "collection",
          "settings": {
            "collection": "fruits-vegetables",
            "image": "shopify:\/\/shop_images\/engin-akyurt-eb26eV-ys_k-unsplash_1.jpg",
            "link": ""
          }
        },
        "5d35b60d-00c8-4df4-94c2-fe4dbfc9e9d1": {
          "type": "collection",
          "settings": {
            "collection": "meat-poultry",
            "link": ""
          }
        },
        "02193e44-62d5-4445-86f9-eb27e8d4bc40": {
          "type": "collection",
          "settings": {
            "collection": "dairy-eggs",
            "image": "shopify:\/\/shop_images\/erol-ahmed-leOh1CzRZVQ-unsplash_1.jpg",
            "link": ""
          }
        },
        "378b72a0-af7d-4dd6-a4d5-9ce8cadf0e49": {
          "type": "collection",
          "settings": {
            "collection": "baking-ingredients",
            "image": "shopify:\/\/shop_images\/Sourdough-Barbari-4.700px.jpg",
            "link": ""
          }
        },
        "05b3eebb-b7fc-49e8-a944-b5e1270c9319": {
          "type": "collection",
          "settings": {
            "collection": "rice-mixes-berenj",
            "image": "shopify:\/\/shop_images\/pierre-bamin--LdilhDx3sk-unsplash_1.jpg",
            "link": ""
          }
        },
        "8df3940a-97fd-46c4-8ba4-448028fc0adf": {
          "type": "collection",
          "settings": {
            "collection": "dried-fruits-nuts",
            "image": "shopify:\/\/shop_images\/engin-akyurt-VkQJDLEPN3w-unsplash_1.jpg",
            "link": ""
          }
        },
        "1b3e6572-160c-4bd6-a9e5-c9a4750688a5": {
          "type": "collection",
          "settings": {
            "collection": "sweets",
            "link": ""
          }
        },
        "2f3c93e5-1f26-4c45-98ce-be1266735be7": {
          "type": "collection",
          "settings": {
            "collection": "canned-vegetables",
            "link": ""
          }
        },
        "3fc3bf75-5c4c-437a-b165-818f69601bfa": {
          "type": "collection",
          "settings": {
            "collection": "herbs",
            "link": ""
          }
        },
        "collection-6": {
          "type": "collection",
          "settings": {
            "collection": "pickled-torshi",
            "image": "shopify:\/\/shop_images\/molin-4C25CSqK2PI-unsplash_1.jpg",
            "link": ""
          }
        },
        "39a201cc-0f08-4bd6-8ee6-0bbda07e938b": {
          "type": "collection",
          "settings": {
            "collection": "pastes",
            "link": ""
          }
        },
        "27dd5be9-fef0-4cc4-b742-9c2de4e72f4f": {
          "type": "collection",
          "settings": {
            "collection": "essence-waters",
            "link": ""
          }
        },
        "942596e4-69e1-4fbc-9954-64c6c2e708fc": {
          "type": "collection",
          "settings": {
            "collection": "jams-syrups",
            "link": ""
          }
        },
        "collection-3": {
          "type": "collection",
          "settings": {
            "collection": "stews-khoresht",
            "link": ""
          }
        },
        "3b61e5da-651f-43de-8341-1fdbb71c30ba": {
          "type": "collection",
          "settings": {
            "collection": "soup-mixes-aash",
            "link": ""
          }
        },
        "collection-4": {
          "type": "collection",
          "settings": {
            "collection": "herb-mixes-sabzi",
            "image": "shopify:\/\/shop_images\/How-to-Use-Dried-Herbs-in-Cooking-culinary-physics.jpg",
            "link": ""
          }
        },
        "1615a069-cecf-4c95-9833-a7732f54eee1": {
          "type": "collection",
          "disabled": true,
          "settings": {
            "collection": "sweets-shirini",
            "link": ""
          }
        },
        "9deeed16-db08-4696-b253-5432c2dfaaeb": {
          "type": "collection",
          "settings": {
            "collection": "stews",
            "link": ""
          }
        },
        "c8f58483-ae4a-4115-b43e-92bff10ce1a7": {
          "type": "collection",
          "disabled": true,
          "settings": {
            "collection": "semi-ready-foods",
            "link": ""
          }
        },
        "f734777c-2248-4d88-a6e5-e2ea527e019b": {
          "type": "collection",
          "disabled": true,
          "settings": {
            "collection": "appetizers",
            "link": ""
          }
        },
        "00e69e4c-42bb-4969-b085-333e5e6558ab": {
          "type": "collection",
          "settings": {
            "collection": "desserts",
            "link": ""
          }
        }
      },
      "block_order": [
        "collection-1",
        "c07d7cd8-49e6-48e6-b89a-8cd1af82b4a1",
        "5d35b60d-00c8-4df4-94c2-fe4dbfc9e9d1",
        "02193e44-62d5-4445-86f9-eb27e8d4bc40",
        "378b72a0-af7d-4dd6-a4d5-9ce8cadf0e49",
        "05b3eebb-b7fc-49e8-a944-b5e1270c9319",
        "8df3940a-97fd-46c4-8ba4-448028fc0adf",
        "1b3e6572-160c-4bd6-a9e5-c9a4750688a5",
        "2f3c93e5-1f26-4c45-98ce-be1266735be7",
        "3fc3bf75-5c4c-437a-b165-818f69601bfa",
        "collection-6",
        "39a201cc-0f08-4bd6-8ee6-0bbda07e938b",
        "27dd5be9-fef0-4cc4-b742-9c2de4e72f4f",
        "942596e4-69e1-4fbc-9954-64c6c2e708fc",
        "collection-3",
        "3b61e5da-651f-43de-8341-1fdbb71c30ba",
        "collection-4",
        "1615a069-cecf-4c95-9833-a7732f54eee1",
        "9deeed16-db08-4696-b253-5432c2dfaaeb",
        "c8f58483-ae4a-4115-b43e-92bff10ce1a7",
        "f734777c-2248-4d88-a6e5-e2ea527e019b",
        "00e69e4c-42bb-4969-b085-333e5e6558ab"
      ],
      "settings": {
        "title": "Our collections",
        "link_title": "View all",
        "link": "shopify:\/\/collections",
        "round_images": true,
        "show_collection_title": true
      }
    },
    "1637543513bbe51b01": {
      "type": "rich-text",
      "settings": {
        "text_width": "regular",
        "title": "",
        "content": "<p>\"They are good in all areas love this company and service\"<\/p><p><\/p><p>Jac Tatarin<\/p>",
        "button_text": "Our products",
        "button_link": ""
      }
    },
    "5c86eb7a-2949-437e-935c-7ae95860f44e": {
      "type": "featured-collection",
      "settings": {
        "collection": "beans-grains",
        "title": "Beans & Grains",
        "products_count": 50,
        "layout": "vertical",
        "stack_products": false,
        "show_quick_buy": false,
        "link_title": "View all",
        "link_url": ""
      }
    },
    "featured-collection": {
      "type": "featured-collection",
      "settings": {
        "collection": "dairy-eggs",
        "title": "Dairy & Eggs",
        "products_count": 50,
        "layout": "vertical",
        "stack_products": false,
        "show_quick_buy": false,
        "link_title": "View all",
        "link_url": "shopify:\/\/collections\/all"
      }
    },
    "df4f318a-e9e1-43e8-a6af-6f57e2301061": {
      "type": "featured-collection",
      "settings": {
        "collection": "fruits-vegetables",
        "title": "Fresh Fruits & Vegetables",
        "products_count": 50,
        "layout": "vertical",
        "stack_products": false,
        "show_quick_buy": false,
        "link_title": "View all",
        "link_url": ""
      }
    },
    "8d007a98-70a1-4f6d-aa32-6261103a70c0": {
      "type": "featured-collection",
      "settings": {
        "collection": "baking-ingredients",
        "title": "Bakery & Naan",
        "products_count": 50,
        "layout": "vertical",
        "stack_products": false,
        "show_quick_buy": false,
        "link_title": "View all",
        "link_url": ""
      }
    },
    "e77139e6-ba29-4c9a-995c-a6f70cdf9ecf": {
      "type": "featured-collection",
      "settings": {
        "collection": "houseware",
        "title": "Household",
        "products_count": 50,
        "layout": "vertical",
        "stack_products": false,
        "show_quick_buy": false,
        "link_title": "View all",
        "link_url": ""
      }
    },
    "1985218e-fd11-4468-9ef3-444935cfe042": {
      "type": "featured-collection",
      "settings": {
        "collection": "meat-poultry",
        "title": "Meat, Fish & Poultry",
        "products_count": 12,
        "layout": "vertical",
        "stack_products": false,
        "show_quick_buy": false,
        "link_title": "View all",
        "link_url": ""
      }
    },
    "text-with-icons": {
      "type": "text-with-icons",
      "disabled": true,
      "blocks": {
        "icon-1": {
          "type": "item",
          "settings": {
            "icon": "bi-delivery",
            "title": "Free delivery worldwide",
            "content": "<p>Short content about your store<\/p>"
          }
        },
        "icon-2": {
          "type": "item",
          "settings": {
            "icon": "bi-returns",
            "title": "Satisfied or refunded",
            "content": "<p>Short content about your store<\/p>"
          }
        },
        "icon-3": {
          "type": "item",
          "settings": {
            "icon": "bi-customer-support",
            "title": "Top-notch support",
            "content": "<p>Short content about your store<\/p>"
          }
        },
        "icon-4": {
          "type": "item",
          "settings": {
            "icon": "bi-secure-payment",
            "title": "Secure payments",
            "content": "<p>Short content about your store<\/p>"
          }
        }
      },
      "block_order": [
        "icon-1",
        "icon-2",
        "icon-3",
        "icon-4"
      ],
      "settings": {
        "stack_mobile": false
      }
    },
    "newsletter": {
      "type": "newsletter",
      "disabled": true,
      "settings": {
        "title": "Newsletter",
        "content": "<p>Sign-up for our Newsletter to hear about our upcoming specials and campaigns.<\/p>",
        "background": "#121251",
        "text": "#ffffff"
      }
    },
    "163624158735e5b47b": {
      "type": "recently-viewed-products",
      "settings": {
        "title": "Recently viewed",
        "show_quick_buy": false
      }
    },
    "blog-posts": {
      "type": "blog-posts",
      "disabled": true,
      "settings": {
        "blog": "",
        "blog_posts_count": 3,
        "title": "Blog posts",
        "link_title": "View all",
        "show_category": true,
        "show_author": true,
        "show_date": true,
        "show_excerpt": false,
        "stack_mobile": false
      }
    },
    "1637542871cef3e060": {
      "type": "slideshow",
      "disabled": true,
      "blocks": {
        "163754287132cb0d7a-0": {
          "type": "image",
          "settings": {
            "show_overlay": false,
            "overlay_opacity": 30,
            "text_color": "#ffffff",
            "title": "Slide title",
            "content": "Tell your story",
            "content_position": "middle_center",
            "button_background": "#ffffff",
            "button_text_color": "#000000",
            "button_text": "Button",
            "link": ""
          }
        },
        "163754287132cb0d7a-1": {
          "type": "image",
          "settings": {
            "show_overlay": false,
            "overlay_opacity": 30,
            "text_color": "#ffffff",
            "title": "Slide title",
            "content": "Tell your story",
            "content_position": "middle_center",
            "button_background": "#ffffff",
            "button_text_color": "#000000",
            "button_text": "Button",
            "link": ""
          }
        }
      },
      "block_order": [
        "163754287132cb0d7a-0",
        "163754287132cb0d7a-1"
      ],
      "settings": {
        "edge_to_edge": true,
        "section_size": "large",
        "carousel_effect": "fade",
        "autoplay": true,
        "cycle_speed": 5
      }
    },
    "survey-modal": {
      "type": "survey-modal",
      "disabled": true,
      "settings": {
        "source": "home",
        "content": "general"
      }
    }
  },
  "order": [
    "165970559810c3db58",
    "slideshow",
    "1636241720a09de843",
    "1637542558ac9160e1",
    "collection-list",
    "1637543513bbe51b01",
    "5c86eb7a-2949-437e-935c-7ae95860f44e",
    "featured-collection",
    "df4f318a-e9e1-43e8-a6af-6f57e2301061",
    "8d007a98-70a1-4f6d-aa32-6261103a70c0",
    "e77139e6-ba29-4c9a-995c-a6f70cdf9ecf",
    "1985218e-fd11-4468-9ef3-444935cfe042",
    "text-with-icons",
    "newsletter",
    "163624158735e5b47b",
    "blog-posts",
    "1637542871cef3e060",
    "survey-modal"
  ]
}
